amphi/__init__.py
amphi/_version.py
amphi/main.py
amphi/theme-light/build_log.json
amphi/theme-light/package.json
amphi/theme-light/static/lib_index_js.b03744e8c5cc1877e003.js
amphi/theme-light/static/lib_index_js.b03744e8c5cc1877e003.js.map
amphi/theme-light/static/remoteEntry.881a18a5050fecade05d.js
amphi/theme-light/static/remoteEntry.881a18a5050fecade05d.js.map
amphi/theme-light/static/style.js
amphi/theme-light/themes/@amphi/theme-light/index.css
amphi/theme-light/themes/@amphi/theme-light/index.js
amphi/ui-component/build_log.json
amphi/ui-component/package.json
amphi/ui-component/static/lib_index_js.375ae4e5428260ad6fca.js
amphi/ui-component/static/lib_index_js.375ae4e5428260ad6fca.js.map
amphi/ui-component/static/remoteEntry.a8ce659d03ded20dc12a.js
amphi/ui-component/static/remoteEntry.a8ce659d03ded20dc12a.js.map
amphi/ui-component/static/style.js
amphi/ui-component/static/style_index_js.4765847abf302fc1ca88.js
amphi/ui-component/static/style_index_js.4765847abf302fc1ca88.js.map
amphi_etl-0.9.3.data/data/etc/jupyter/labconfig/page_config.json
amphi_etl-0.9.3.data/data/share/jupyter/lab/settings/overrides.json
amphi_etl-0.9.3.data/data/share/jupyter/labextensions/@amphi/__init__.py
amphi_etl-0.9.3.data/data/share/jupyter/labextensions/@amphi/_version.py
amphi_etl-0.9.3.data/data/share/jupyter/labextensions/@amphi/main.py
amphi_etl-0.9.3.data/data/share/jupyter/labextensions/@amphi/theme-light/build_log.json
amphi_etl-0.9.3.data/data/share/jupyter/labextensions/@amphi/theme-light/package.json
amphi_etl-0.9.3.data/data/share/jupyter/labextensions/@amphi/theme-light/static/lib_index_js.b03744e8c5cc1877e003.js
amphi_etl-0.9.3.data/data/share/jupyter/labextensions/@amphi/theme-light/static/lib_index_js.b03744e8c5cc1877e003.js.map
amphi_etl-0.9.3.data/data/share/jupyter/labextensions/@amphi/theme-light/static/remoteEntry.881a18a5050fecade05d.js
amphi_etl-0.9.3.data/data/share/jupyter/labextensions/@amphi/theme-light/static/remoteEntry.881a18a5050fecade05d.js.map
amphi_etl-0.9.3.dist-info/LICENSE
amphi_etl-0.9.3.dist-info/METADATA
amphi_etl-0.9.3.dist-info/WHEEL
amphi_etl-0.9.3.dist-info/entry_points.txt
amphi_etl-0.9.3.dist-info/top_level.txt
amphi_etl-0.9.3.dist-info/RECORD
