Metadata-Version: 2.1
Name: amphi-etl
Version: 0.9.3
Summary: Open-source and Python-based ETL
Home-page: UNKNOWN
Author: Thibaut Gourdel
Author-email: tgourdel@amphi.ai
License: ELv2
Platform: UNKNOWN
License-File: LICENSE
Requires-Dist: jupyterlab==4.5.2
Requires-Dist: jupyterlab-amphi==0.9.2
Requires-Dist: amphi-scheduler==0.9.2
Requires-Dist: pandas>=2.0
